facedancer/HIDClass.py
facedancer/USB.py
facedancer/USBClass.py
facedancer/USBConfiguration.py
facedancer/USBDevice.py
facedancer/USBEndpoint.py
facedancer/USBInterface.py
facedancer/USBProxy.py
facedancer/USBVendor.py
facedancer/__init__.py
facedancer/core.py
facedancer/errors.py
facedancer/backends/GoodFETMaxUSBApp.py
facedancer/backends/GreatDancerApp.py
facedancer/backends/GreatDancerHostApp.py
facedancer/backends/LibUSBHostApp.py
facedancer/backends/MAXUSBApp.py
facedancer/backends/RaspdancerMaxUSBApp.py
facedancer/backends/__init__.py
facedancer/filters/__init__.py
facedancer/filters/logging.py
facedancer/filters/standard.py
facedancer-2019.3.2.dist-info/LICENSE
facedancer-2019.3.2.dist-info/METADATA
facedancer-2019.3.2.dist-info/WHEEL
facedancer-2019.3.2.dist-info/top_level.txt
facedancer-2019.3.2.dist-info/RECORD
