Metadata-Version: 2.1
Name: facedancer
Version: 2019.3.2
Summary: Python library for emulating USB devices
Home-page: https://greatscottgadgets.com/greatfet/
Maintainer: Katherine J. Temkin
Maintainer-email: k@ktemkin.com
License: BSD
Platform: any
Classifier: Development Status :: 4 - Beta
Classifier: Natural Language :: English
Classifier: Environment :: Console
Classifier: Environment :: Plugins
Classifier: Intended Audience :: Developers
Classifier: Intended Audience :: Science/Research
Classifier: License :: OSI Approved :: BSD License
Classifier: Operating System :: OS Independent
Classifier: Topic :: Scientific/Engineering
Classifier: Topic :: Security
Classifier: Programming Language :: Python
Classifier: Programming Language :: Python :: 3
Requires-Dist: pyusb
